{
  "users": [
    {
      "name": "test",
      "email": "adm@gmail.com",
      "password": "admin123ggggg",
      "id": 1
    },
    {
      "name": "test2",
      "email": "admin@gmail.com",
      "password": "admin123ggggg",
      "id": 2
    }
  ],
  "notes": [
    {
      "name": "dfgsrgs",
      "date": "2023-01-04",
      "remark": "333",
      "userId": "1",
      "userName": "test",
      "number": 4,
      "id": 1
    },
    {
      "name": "notes1",
      "date": "2022-12-28",
      "remark": "remark",
      "userId": "2",
      "userName": "test2",
      "number": 1,
      "id": 2
    },
    {
      "name": "srgfdfbsf",
      "date": "2023-01-04",
      "remark": "32232332",
      "userId": "2",
      "userName": "test2",
      "number": 45,
      "id": 3
    },
    {
      "name": "fgggg",
      "date": "2023-01-04",
      "remark": null,
      "userId": "2",
      "userName": "test2",
      "currentDate": "2023-01-03T13:39:28.195Z",
      "number": 5,
      "id": 4
    },
    {
      "name": "ddddd",
      "date": "2023-01-12",
      "remark": null,
      "userId": "2",
      "userName": "test2",
      "currentDate": "03/01/2023",
      "number": 7,
      "id": 5
    }
  ]
}